API.rst
MANIFEST.in
README.rst
setup.py
src/bda/__init__.py
src/bda.plone.finder.egg-info/PKG-INFO
src/bda.plone.finder.egg-info/SOURCES.txt
src/bda.plone.finder.egg-info/dependency_links.txt
src/bda.plone.finder.egg-info/entry_points.txt
src/bda.plone.finder.egg-info/namespace_packages.txt
src/bda.plone.finder.egg-info/not-zip-safe
src/bda.plone.finder.egg-info/requires.txt
src/bda.plone.finder.egg-info/top_level.txt
src/bda/plone/__init__.py
src/bda/plone/finder/__init__.py
src/bda/plone/finder/configure.zcml
src/bda/plone/finder/interfaces.py
src/bda/plone/finder/profile.zcml
src/bda/plone/finder/browser/__init__.py
src/bda/plone/finder/browser/actions.py
src/bda/plone/finder/browser/actions.zcml
src/bda/plone/finder/browser/column.py
src/bda/plone/finder/browser/configure.zcml
src/bda/plone/finder/browser/details.py
src/bda/plone/finder/browser/details.zcml
src/bda/plone/finder/browser/finder.py
src/bda/plone/finder/browser/folderish.py
src/bda/plone/finder/browser/folderish.zcml
src/bda/plone/finder/browser/menu.py
src/bda/plone/finder/browser/menu.zcml
src/bda/plone/finder/browser/provider.py
src/bda/plone/finder/browser/provider.zcml
src/bda/plone/finder/browser/utils.py
src/bda/plone/finder/browser/images/add.png
src/bda/plone/finder/browser/images/add_disabled.png
src/bda/plone/finder/browser/images/apple_close.png
src/bda/plone/finder/browser/images/arrow_left_right.png
src/bda/plone/finder/browser/images/arrow_right.png
src/bda/plone/finder/browser/images/blank.gif
src/bda/plone/finder/browser/images/change_state.png
src/bda/plone/finder/browser/images/change_state_disabled.png
src/bda/plone/finder/browser/images/copy.png
src/bda/plone/finder/browser/images/copy_disabled.png
src/bda/plone/finder/browser/images/cut.png
src/bda/plone/finder/browser/images/cut_disabled.png
src/bda/plone/finder/browser/images/delete.png
src/bda/plone/finder/browser/images/delete_disabled.png
src/bda/plone/finder/browser/images/edit.png
src/bda/plone/finder/browser/images/edit_disabled.png
src/bda/plone/finder/browser/images/error_icon.png
src/bda/plone/finder/browser/images/info_icon.png
src/bda/plone/finder/browser/images/paste.png
src/bda/plone/finder/browser/images/paste_disabled.png
src/bda/plone/finder/browser/images/view.png
src/bda/plone/finder/browser/images/view_disabled.png
