Metadata-Version: 1.1
Name: bda.plone.finder
Version: 1.3
Summary: Mac Finder like view for Plone.
Home-page: https://github.com/collective/bda.plone.finder
Author: Robert Niederreiter
Author-email: dev@bluedynamics.com
License: GNU General Public Licence
Platform: UNKNOWN
Classifier: Environment :: Web Environment
Classifier: License :: OSI Approved :: GNU General Public License (GPL)
Classifier: Operating System :: OS Independent
Classifier: Programming Language :: Python
Classifier: Topic :: Internet :: WWW/HTTP :: Dynamic Content
